<sounds root="sounds/jotaro/">
	<sound name="Stand_PunchLight">
		<sample weight="1" path="punchLight.wav" />
	</sound>
	<sound name="Stand_PunchHeavy">
		<sample weight="1" path="punchHeavy.wav" />
	</sound>
	<sound name="Stand_Whoosh">
		<sample weight="1" path="whoosh.wav" />
	</sound>
	<sound name="Stand_PunchReady">
		<sample weight="1" path="ready.wav" />
	</sound>
	<sound name="Stand_Rage">
		<sample weight="1" path="rage.wav" />
	</sound>
	<sound name="StarPlatinum_CryStart">
		<sample weight="1" path="cryStart.wav" />
	</sound>
	<sound name="StarPlatinum_CryMid">
		<sample weight="1" path="cryMid.wav" />
	</sound>
	<sound name="StarPlatinum_CryFinish">
		<sample weight="1" path="cryFinish.wav" />
	</sound>
	<sound name="StarPlatinum_Cry">
		<sample weight="1" path="cryUnique.wav" />
	</sound>
    <sound name="StarPlatinum_ZaWarudo">
		<sample weight="1" path="starPlatinumZaWarudo.wav"/>
	</sound>
	<sound name="StopTime">
		<sample weight="1" path="timeStop.wav"/>
	</sound>
	<sound name="ResumeTime">
		<sample weight="1" path="timeResume.wav"/>
	</sound>
	<sound name="Tick5">
		<sample weight="1" path="ticking5.wav"/>
	</sound>
	<sound name="Tick9">
		<sample weight="1" path="ticking9.wav"/>
	</sound>
</sounds>